{
  "id": "prt_962047410001dpdGHP1UoNn6Pb",
  "messageID": "msg_96203b609001luYpYwXTijbJkN",
  "sessionID": "ses_6a7af0913ffePKeafEVjU8Zw0Y",
  "type": "tool",
  "tool": "read",
  "callID": "toolu_01F4CViYiiuiZ1Sk6JSWeAxt",
  "state": {
    "status": "completed",
    "input": {
      "filePath": "/home/user/project/app/subtype-advisor/page.tsx",
      "offset": 280,
      "limit": 30
    },
    "output": "<file>\n00281|                       {primarySubtype.treatments.nonPharmacological.map((treatment, index) => (\n00282|                         <li key={index} className=\"flex items-start gap-2\">\n00283|                           <span className=\"text-green-600 mt-1\">•</span>\n00284|                           {treatment}\n00285|                         </li>\n00286|                       ))}\n00287|                     </ul>\n00288|                   </CardContent>\n00289|                 </Card>\n00290| \n00291|                 <Card className=\"border-blue-200 bg-blue-50\">\n00292|                   <CardHeader className=\"pb-3\">\n00293|                     <CardTitle className=\"text-lg text-blue-800 flex items-center gap-2\">\n00294|                       <Pill className=\"h-5 w-5\" />\n00295|                       {t.subtype.results.firstLineRx}\n00296|                     </CardTitle>\n00297|                   </CardHeader>\n00298|                   <CardContent>\n00299|                     <ul className=\"space-y-2 text-sm\">\n00300|                       {primarySubtype.treatments.firstLine.map((treatment, index) => (\n00301|                         <li key={index} className=\"flex items-start gap-2\">\n00302|                           <span className=\"text-blue-600 mt-1\">•</span>\n00303|                           {treatment}\n00304|                         </li>\n00305|                       ))}\n00306|                     </ul>\n00307|                   </CardContent>\n00308|                 </Card>\n00309| \n00310|                 <Card className=\"border-purple-200 bg-purple-50\">\n\n(File has more lines. Use 'offset' parameter to read beyond line 310)\n</file>",
    "metadata": {
      "preview": "                      {primarySubtype.treatments.nonPharmacological.map((treatment, index) => (\n                        <li key={index} className=\"flex items-start gap-2\">\n                          <span className=\"text-green-600 mt-1\">•</span>\n                          {treatment}\n                        </li>\n                      ))}\n                    </ul>\n                  </CardContent>\n                </Card>\n\n                <Card className=\"border-blue-200 bg-blue-50\">\n                  <CardHeader className=\"pb-3\">\n                    <CardTitle className=\"text-lg text-blue-800 flex items-center gap-2\">\n                      <Pill className=\"h-5 w-5\" />\n                      {t.subtype.results.firstLineRx}\n                    </CardTitle>\n                  </CardHeader>\n                  <CardContent>\n                    <ul className=\"space-y-2 text-sm\">\n                      {primarySubtype.treatments.firstLine.map((treatment, index) => ("
    },
    "title": "app/subtype-advisor/page.tsx",
    "time": {
      "start": 1758286083614,
      "end": 1758286083616
    }
  }
}