{
  "id": "prt_95bbca0e7001ys50V5TibTkQwl",
  "messageID": "msg_95bbbfb8e001gCGY7lcwUNBnji",
  "sessionID": "ses_6a7af0913ffePKeafEVjU8Zw0Y",
  "type": "tool",
  "tool": "edit",
  "callID": "toolu_01JNixuP9HVKGr4e4Q3zotGL",
  "state": {
    "status": "completed",
    "input": {
      "filePath": "/home/user/project/lib/translations/en.ts",
      "oldString": "    creator: {\n      title: 'Creator & License',\n      createdBy: 'Created by',\n      name: 'Willem Gielen MD',\n      organization: 'Nordjysk Speciallaegeklinik',\n      location: 'Hjørring, Denmark',\n      license: 'Open source under MIT License',\n      linkedinProfile: 'LinkedIn Profile',\n      organizationWebsite: 'Organization Website'\n    },",
      "newString": "    creator: {\n      title: 'Creator & License',\n      createdBy: 'Created by',\n      name: 'Willem Gielen MD',\n      organization: 'Nordjysk Speciallaegeklinik',\n      location: 'Hjørring, Denmark',\n      license: 'Open source under MIT License',\n      linkedinProfile: 'LinkedIn Profile',\n      organizationWebsite: 'Organization Website',\n      githubRepository: 'GitHub Repository'\n    },"
    },
    "output": "",
    "metadata": {
      "diagnostics": {},
      "diff": "Index: /home/user/project/lib/translations/en.ts\n===================================================================\n--- /home/user/project/lib/translations/en.ts\n+++ /home/user/project/lib/translations/en.ts\n@@ -808,9 +808,10 @@\n   organization: 'Nordjysk Speciallaegeklinik',\n   location: 'Hjørring, Denmark',\n   license: 'Open source under MIT License',\n   linkedinProfile: 'LinkedIn Profile',\n-  organizationWebsite: 'Organization Website'\n+  organizationWebsite: 'Organization Website',\n+  githubRepository: 'GitHub Repository'\n },\n evidence: {\n   title: 'Evidence Base',\n   guidelines: [\n"
    },
    "title": "lib/translations/en.ts",
    "time": {
      "start": 1758180715056,
      "end": 1758180715076
    }
  }
}