{
  "id": "prt_96209fe59001fzierXGa4WV7oz",
  "messageID": "msg_96206abc7001E3qxqFDMYTHHcM",
  "sessionID": "ses_6a7af0913ffePKeafEVjU8Zw0Y",
  "type": "tool",
  "tool": "read",
  "callID": "toolu_01A3MQvozPvVkwDZ1HpdXgQ8",
  "state": {
    "status": "completed",
    "input": {
      "filePath": "/home/user/project/app/subtype-advisor/page.tsx",
      "offset": 58,
      "limit": 10
    },
    "output": "<file>\n00059|       description: desc,\n00060|       checked: false\n00061|     })),\n00062|     treatments: {\n00063|       nonPharmacological: t.subtype.subtypes.neuropathic.treatments.nonPharmacological,\n00064|       firstLine: t.subtype.subtypes.neuropathic.treatments.firstLine,\n00065|       secondLine: t.subtype.subtypes.neuropathic.treatments.secondLine\n00066|     }\n00067|   },\n00068|   {\n\n(File has more lines. Use 'offset' parameter to read beyond line 68)\n</file>",
    "metadata": {
      "preview": "      description: desc,\n      checked: false\n    })),\n    treatments: {\n      nonPharmacological: t.subtype.subtypes.neuropathic.treatments.nonPharmacological,\n      firstLine: t.subtype.subtypes.neuropathic.treatments.firstLine,\n      secondLine: t.subtype.subtypes.neuropathic.treatments.secondLine\n    }\n  },\n  {"
    },
    "title": "app/subtype-advisor/page.tsx",
    "time": {
      "start": 1758286446757,
      "end": 1758286446759
    }
  }
}